pytest_directives/__init__.py
pytest_directives/pytest_directives.py
pytest_directives/core/__init__.py
pytest_directives/core/abc_directive.py
pytest_directives/core/run_strategies.py
pytest_directives/core/utils/__init__.py
pytest_directives/core/utils/devide.py
pytest_directives-0.0.3.dist-info/licenses/LICENSE
pytest_directives-0.0.3.dist-info/METADATA
pytest_directives-0.0.3.dist-info/WHEEL
pytest_directives-0.0.3.dist-info/top_level.txt
pytest_directives-0.0.3.dist-info/RECORD
